{
  "db": "PostgreSQL",
  "619abb60a7bc64180bc348b6e103c5db0bdf45283c187ee9d79381270fe63221": {
    "describe": {
      "columns": [
        {
          "name": "id",
          "ordinal": 0,
          "type_info": "Uuid"
        },
        {
          "name": "username",
          "ordinal": 1,
          "type_info": "Varchar"
        },
        {
          "name": "email",
          "ordinal": 2,
          "type_info": "Varchar"
        },
        {
          "name": "password",
          "ordinal": 3,
          "type_info": "Varchar"
        },
        {
          "name": "locked",
          "ordinal": 4,
          "type_info": "Bool"
        },
        {
          "name": "last_login",
          "ordinal": 5,
          "type_info": "Timestamptz"
        },
        {
          "name": "created_at",
          "ordinal": 6,
          "type_info": "Timestamptz"
        }
      ],
      "nullable": [
        false,
        true,
        true,
        false,
        false,
        true,
        false
      ],
      "parameters": {
        "Left": [
          "Uuid"
        ]
      }
    },
    "query": "\n            SELECT u.*\n            FROM users u\n            WHERE u.id = $1\n            "
  }
}